pegasus_wrapper/__init__.py
pegasus_wrapper/artifact.py
pegasus_wrapper/conda_job_script.py
pegasus_wrapper/docker_job_script.py
pegasus_wrapper/key_value.py
pegasus_wrapper/locator.py
pegasus_wrapper/pegasus_container.py
pegasus_wrapper/pegasus_profile.py
pegasus_wrapper/pegasus_transformation.py
pegasus_wrapper/pegasus_utils.py
pegasus_wrapper/resource_request.py
pegasus_wrapper/version.py
pegasus_wrapper/workflow.py
pegasus_wrapper/scripts/__init__.py
pegasus_wrapper/scripts/add_y.py
pegasus_wrapper/scripts/example_container_workflow_builder.py
pegasus_wrapper/scripts/example_workflow_builder.py
pegasus_wrapper/scripts/multiply_by_x.py
pegasus_wrapper/scripts/nuke_checkpoints.py
pegasus_wrapper/scripts/sort_nums_in_file.py
tests/__init__.py
tests/helper_class_test.py
tests/key_value_test.py
tests/workflow_builder_test.py
tests/workflow_test.py
pegasus_wrapper-0.4.0.dist-info/LICENSE
pegasus_wrapper-0.4.0.dist-info/METADATA
pegasus_wrapper-0.4.0.dist-info/WHEEL
pegasus_wrapper-0.4.0.dist-info/top_level.txt
pegasus_wrapper-0.4.0.dist-info/RECORD
