Metadata-Version: 2.1
Name: pegasus-wrapper
Version: 0.4.0
Summary: A higher-level API for ISI Pegasus, adapted to the quirks of the ISI Vista group
Home-page: https://github.com/isi-vista/vista-pegasus-wrapper
Author: Jacob Lichtefeld, Ryan Gabbard
Author-email: jalichtefeld@gmail.com,ryan.gabbard@gmail.com
License: UNKNOWN
Platform: UNKNOWN
Classifier: Programming Language :: Python :: 3
Classifier: License :: OSI Approved :: MIT License
Classifier: Operating System :: OS Independent
Requires-Python: ~=3.6
Requires-Dist: importlib-resources (==1.4.0)
Requires-Dist: vistautils (>=0.21.0)
Requires-Dist: gitpython (>=3.1.12)
Requires-Dist: pegasus-wms.api (==5.0.0)
Requires-Dist: more-itertools (>=8.2.0)
